{
  "date": "2020-04-22T02:46:29.436Z",
  "title": "モノ記【No.1】～初めての記事、サイト開設の経緯",
  "description": "初回記事です！テスト用でもありますよー！",
  "body": "みなさんこんにちは！モノクロコードと申すものです！\n\n今回は、サイト開設初の記事ということで、今回のモノクロコード公式ホームページ、MONOtown綴りたいと思います！\n\n本格的な活動を始めるにあたって、「公式サイト」という”僕の情報だけが集まる場所”は必要不可欠でした。\\\n今まではTwitterなどで事足りていました。しかし、これからの活動の発展を見据えた場合、作る以外の考えは沈むのは当然のこと。僕は思い立つ成り行動に移しました。\n\nサイトのデザインを考えるのは容易が、それを形にする力が僕にはありませんでした。\\\n足は確かに生えていれど、歩み方を知らないのです。\\\nただ、僕にとってそれは些細な問題にすらなりませんでした。\n\n「僕の足を使い、歩める人間」にアテがからです。\n\n僕の兄minato86は、多くの人間の代わりに歩みを進めてきたウェブデザイナーであり、ずっと近くで憧れてきた僕にとって、その技術と熱意は疑うという言葉の存在すら危うくなるほどに、確定的な才でした。\n\n兄に、素材とデザイン案を渡し、僕の未来の作成を依頼しました。\\\n兄弟といっても依頼主とプロのクリエイター。勿論敬意と依頼料を払いました。\n\nそれに応えるように兄はプロとして依頼主である僕が満足できるクオリティで提供してくれました。\\\nいつも横顔しか見てこなかった、プロとしての兄の目を見ることができた気がします。\n\n本当にありがとう。\n\n皆さんもサイト等を開設する際は！僕の兄minato86に依頼してみてくださいね！",
  "author": "モノクロコード"
}